pywisp/__init__.py
pywisp/connection.py
pywisp/experimentModules.py
pywisp/experiments.py
pywisp/gamepad.py
pywisp/gui.py
pywisp/inputs.py
pywisp/min.py
pywisp/registry.py
pywisp/settings.py
pywisp/utils.py
pywisp/visualization.py
pywisp/resources/__init__.py
pywisp/resources/colors.py
pywisp/resources/gpPS4-LinuxDefault.yaml
pywisp/resources/gpPS4-WinDefault.yaml
pywisp/resources/logging.conf
pywisp/resources/logging.yaml
pywisp/resources/icons/connected.png
pywisp/resources/icons/disconnected.png
pywisp/resources/icons/icon.ico
pywisp/resources/icons/icon.pdf
pywisp/resources/icons/icon.png
pywisp/resources/icons/icon.svg
pywisp/resources/icons/icon128.png
pywisp/resources/icons/icon32.png
pywisp/resources/icons/load.png
pywisp/resources/icons/play.png
pywisp/resources/icons/save.png
pywisp/resources/icons/stop.png
pywisp/widgets/fileselector.py
pywisp/widgets/plotchart.py
pywisp-1.1.1.dist-info/licenses/LICENSE
pywisp-1.1.1.dist-info/METADATA
pywisp-1.1.1.dist-info/WHEEL
pywisp-1.1.1.dist-info/top_level.txt
pywisp-1.1.1.dist-info/RECORD
